setup.py
swirl.py
swirl.egg-info/PKG-INFO
swirl.egg-info/SOURCES.txt
swirl.egg-info/dependency_links.txt
swirl.egg-info/top_level.txt