Metadata-Version: 1.0
Name: swirl
Version: 0.1.2
Summary: Some sugar for asynchronous Tornado code
Home-page: http://code.naeseth.com/swirl/
Author: Eric Naeseth
Author-email: eric@naeseth.com
License: UNKNOWN
Platform: UNKNOWN
